README.rst
setup.py
rvo/__init__.py
rvo/analysis.py
rvo/cli.py
rvo/config.py
rvo/crypto.py
rvo/db.py
rvo/transaction.py
rvo/utils.py
rvo/validate.py
rvo/views.py
rvo.egg-info/PKG-INFO
rvo.egg-info/SOURCES.txt
rvo.egg-info/dependency_links.txt
rvo.egg-info/entry_points.txt
rvo.egg-info/requires.txt
rvo.egg-info/top_level.txt
rvo.egg-info/zip-safe
rvo/commands/__init__.py
rvo/commands/add.py
rvo/commands/append.py
rvo/commands/delete.py
rvo/commands/edit.py
rvo/commands/export.py
rvo/commands/info.py
rvo/commands/list.py
rvo/commands/log.py
rvo/commands/mail.py
rvo/commands/memories.py
rvo/commands/modify.py
rvo/commands/ping.py
rvo/commands/rimport.py
rvo/commands/show.py
rvo/commands/stats.py