Metadata-Version: 1.1
Name: rvo
Version: 21.0.0
Summary: Managing text data from the commandline
Home-page: https://github.com/noqqe/rvo
Author: Florian Baumann
Author-email: flo@noqqe.de
License: MIT
Keywords: links mongodb quotes notes journal diary
Platform: UNKNOWN
Classifier: Development Status :: 5 - Production/Stable
Classifier: Environment :: Console
Classifier: Operating System :: POSIX :: BSD :: OpenBSD
Classifier: Topic :: Terminals
Classifier: Topic :: Utilities
Classifier: Topic :: Documentation
Classifier: License :: OSI Approved :: MIT License
Classifier: Programming Language :: Python :: 2.7
